vnlp/__init__.py
vnlp/utils.py
vnlp/bin/__init__.py
vnlp/bin/vnlp.py
vnlp/dependency_parser/ReadMe.md
vnlp/dependency_parser/__init__.py
vnlp/dependency_parser/_spu_context_utils.py
vnlp/dependency_parser/_treestack_utils.py
vnlp/dependency_parser/dependency_parser.py
vnlp/dependency_parser/spu_context_dp.py
vnlp/dependency_parser/treestack_dp.py
vnlp/dependency_parser/utils.py
vnlp/dependency_parser/resources/DP_label_tokenizer.json
vnlp/named_entity_recognizer/ReadMe.md
vnlp/named_entity_recognizer/__init__.py
vnlp/named_entity_recognizer/_charner_utils.py
vnlp/named_entity_recognizer/_spu_context_utils.py
vnlp/named_entity_recognizer/charner.py
vnlp/named_entity_recognizer/named_entity_recognizer.py
vnlp/named_entity_recognizer/spu_context_ner.py
vnlp/named_entity_recognizer/utils.py
vnlp/named_entity_recognizer/resources/CharNER_char_tokenizer.json
vnlp/named_entity_recognizer/resources/NER_label_tokenizer.json
vnlp/normalizer/ReadMe.md
vnlp/normalizer/__init__.py
vnlp/normalizer/_deasciifier.py
vnlp/normalizer/normalizer.py
vnlp/part_of_speech_tagger/ReadMe.md
vnlp/part_of_speech_tagger/__init__.py
vnlp/part_of_speech_tagger/_spu_context_utils.py
vnlp/part_of_speech_tagger/_treestack_utils.py
vnlp/part_of_speech_tagger/part_of_speech_tagger.py
vnlp/part_of_speech_tagger/spu_context_pos.py
vnlp/part_of_speech_tagger/treestack_pos.py
vnlp/part_of_speech_tagger/resources/PoS_label_tokenizer.json
vnlp/resources/SPU_word_tokenizer_16k.model
vnlp/resources/TB_word_tokenizer.json
vnlp/resources/non_breaking_prefixes_tr.txt
vnlp/resources/turkish_known_words_lexicon.txt
vnlp/resources/turkish_stop_words.txt
vnlp/sentence_splitter/ReadMe.md
vnlp/sentence_splitter/__init__.py
vnlp/sentence_splitter/sentence_splitter.py
vnlp/sentiment_analyzer/ReadMe.md
vnlp/sentiment_analyzer/__init__.py
vnlp/sentiment_analyzer/_spu_context_bigru_utils.py
vnlp/sentiment_analyzer/sentiment_analyzer.py
vnlp/sentiment_analyzer/spu_context_bigru_sentiment.py
vngrs_nlp-0.2.4.dist-info/LICENSE
vngrs_nlp-0.2.4.dist-info/METADATA
vngrs_nlp-0.2.4.dist-info/WHEEL
vngrs_nlp-0.2.4.dist-info/entry_points.txt
vngrs_nlp-0.2.4.dist-info/top_level.txt
vngrs_nlp-0.2.4.dist-info/RECORD
