Metadata-Version: 2.1
Name: vngrs-nlp
Version: 0.2.4
Summary: Turkish NLP Tools developed by VNGRS.
Author: Meliksah Turker
Author-email: turkermeliksah@hotmail.com
License: GNU Affero General Public License v3.0
Project-URL: Homepage, https://github.com/vngrs-ai/vnlp
Project-URL: Documentation, https://vnlp.readthedocs.io/en/latest/
Project-URL: Website, https://vnlp.io
Classifier: Development Status :: 3 - Alpha
Classifier: Intended Audience :: Developers
Classifier: Intended Audience :: Education
Classifier: Intended Audience :: Science/Research
Classifier: Intended Audience :: Information Technology
Classifier: Topic :: Scientific/Engineering
Classifier: Topic :: Scientific/Engineering :: Artificial Intelligence
Classifier: Topic :: Scientific/Engineering :: Information Analysis
Classifier: Topic :: Text Processing
Classifier: Topic :: Text Processing :: Linguistic
Classifier: Topic :: Software Development
Classifier: Topic :: Software Development :: Libraries
Classifier: Programming Language :: Python
Classifier: Programming Language :: Python :: 3
Classifier: Programming Language :: Python :: 3.7
Classifier: Programming Language :: Python :: 3.8
Classifier: Programming Language :: Python :: 3.9
Classifier: Programming Language :: Python :: 3.10
Classifier: Programming Language :: Python :: 3.11
License-File: LICENSE
Requires-Dist: tensorflow<2.6.0; python_version < "3.8"
Requires-Dist: tensorflow<2.16,>=2.6; python_version >= "3.8"
Requires-Dist: regex
Requires-Dist: requests
Requires-Dist: sentencepiece
Provides-Extra: extras
Requires-Dist: gensim; extra == "extras"
Requires-Dist: spacy; extra == "extras"
Provides-Extra: develop
Requires-Dist: pre-commit; extra == "develop"
Requires-Dist: pytest; extra == "develop"
